bucket_locker/__init__.py
bucket_locker/bucket_locker.py
bucket_locker-1.0.8.dist-info/licenses/LICENSE
bucket_locker-1.0.8.dist-info/METADATA
bucket_locker-1.0.8.dist-info/WHEEL
bucket_locker-1.0.8.dist-info/top_level.txt
bucket_locker-1.0.8.dist-info/RECORD
