Metadata-Version: 2.4
Name: bucket_locker
Version: 1.0.8
Summary: A Python library that synchronizes local files with Google Cloud Storage in a concurrency-aware manner.
Author-email: Nadia Polikarpova <nadia.polikarpova@gmail.com>
License: MIT license
Project-URL: homepage, https://github.com/nadia-polikarpova/bucket-locker
License-File: LICENSE
Requires-Dist: google-cloud-storage
Provides-Extra: dev
Requires-Dist: pytest>=8.0; extra == "dev"
Requires-Dist: pytest-asyncio>=0.23; extra == "dev"
Dynamic: license-file
